soaplite/__init__.py
soaplite/genBasis.py
soaplite/soapPy.py
soaplite/src/libsoapPy.so
soaplite/src/libsoapPy2.so
soaplite/src/libsoapPy3.so
soaplite/src/libsoapPy4.so
soaplite/src/libsoapPy5.so
soaplite/src/libsoapPy6.so
soaplite-0.9.10.dist-info/DESCRIPTION.rst
soaplite-0.9.10.dist-info/LICENSE.txt
soaplite-0.9.10.dist-info/METADATA
soaplite-0.9.10.dist-info/RECORD
soaplite-0.9.10.dist-info/WHEEL
soaplite-0.9.10.dist-info/metadata.json
soaplite-0.9.10.dist-info/top_level.txt
